optilab/__init__.py
optilab/__main__.py
optilab/data_classes/__init__.py
optilab/data_classes/bounds.py
optilab/data_classes/function_metadata.py
optilab/data_classes/optimization_run.py
optilab/data_classes/optimizer_metadata.py
optilab/data_classes/point.py
optilab/data_classes/point_list.py
optilab/functions/__init__.py
optilab/functions/noisy_function.py
optilab/functions/objective_function.py
optilab/functions/benchmarks/__init__.py
optilab/functions/benchmarks/cec_objective_function.py
optilab/functions/multimodal/__init__.py
optilab/functions/multimodal/ackley_function.py
optilab/functions/multimodal/rastrigin_function.py
optilab/functions/multimodal/rosenbrock_function.py
optilab/functions/surrogate/__init__.py
optilab/functions/surrogate/knn_surrogate_objective_function.py
optilab/functions/surrogate/locally_weighted_polynomial_regression.py
optilab/functions/surrogate/polynomial_regression.py
optilab/functions/surrogate/surrogate_objective_function.py
optilab/functions/unimodal/__init__.py
optilab/functions/unimodal/bent_cigar_function.py
optilab/functions/unimodal/cumulative_squared_sums.py
optilab/functions/unimodal/increasing_weight_cigar.py
optilab/functions/unimodal/linear_function.py
optilab/functions/unimodal/sphere_function.py
optilab/metamodels/__init__.py
optilab/metamodels/approximate_ranking_metamodel.py
optilab/metamodels/iepolation_surrogate.py
optilab/optimizers/__init__.py
optilab/optimizers/cma_es.py
optilab/optimizers/ipop_cma_es.py
optilab/optimizers/knn_cma_es.py
optilab/optimizers/knn_ipop_cma_es.py
optilab/optimizers/lmm_cma_es.py
optilab/optimizers/optimizer.py
optilab/plotting/__init__.py
optilab/plotting/box_plot.py
optilab/plotting/convergence_curve.py
optilab/plotting/ecdf_curve.py
optilab/utils/__init__.py
optilab/utils/aggregate_pvalues.py
optilab/utils/aggregate_stats.py
optilab/utils/pickle_utils.py
optilab/utils/stat_test.py
optilab-27.dist-info/licenses/LICENSE
optilab-27.dist-info/METADATA
optilab-27.dist-info/WHEEL
optilab-27.dist-info/entry_points.txt
optilab-27.dist-info/top_level.txt
optilab-27.dist-info/RECORD
