Metadata-Version: 2.4
Name: optilab
Version: 27
Summary: Simple framework for optimization functions and metamodels
Author-email: mlojek <marcin.lojek@pw.edu.pl>
Project-URL: Homepage, https://github.com/mlojek/optilab
Classifier: License :: OSI Approved :: GNU General Public License v3 (GPLv3)
Classifier: Operating System :: OS Independent
Classifier: Programming Language :: Python :: 3
Requires-Python: >=3.11.9
License-File: LICENSE
Requires-Dist: black
Requires-Dist: cma==4.0.0
Requires-Dist: faiss-cpu
Requires-Dist: isort
Requires-Dist: jupyter
Requires-Dist: matplotlib==3.9.2
Requires-Dist: numpy==2.1.3
Requires-Dist: opfunu==1.0.0
Requires-Dist: pandas==2.2.3
Requires-Dist: pre-commit
Requires-Dist: pylint
Requires-Dist: pyprojectsort
Requires-Dist: pytest
Requires-Dist: scikit-learn==1.5.2
Requires-Dist: setuptools
Requires-Dist: shapely==2.0.6
Requires-Dist: sphinx
Requires-Dist: sphinx-rtd-theme
Requires-Dist: tabulate
Requires-Dist: tqdm
Requires-Dist: typing
Requires-Dist: zstandard
Dynamic: license-file
